dlight/__init__.py
dlight.py-0.0.4.dist-info/METADATA
dlight.py-0.0.4.dist-info/WHEEL
dlight.py-0.0.4.dist-info/top_level.txt
dlight.py-0.0.4.dist-info/RECORD
