Metadata-Version: 2.1
Name: dlight.py
Version: 0.0.4
Summary: Python api wrapper for daylight/DLIGHT
Home-page: https://dlight-py.gitbook.io/dlight-py/
Author: Andromeda
Author-email: and@rjbot.xyz
License: MIT
Keywords: dlight
Platform: UNKNOWN
Classifier: Development Status :: 5 - Production/Stable
Classifier: Intended Audience :: Developers
Classifier: Operating System :: Microsoft :: Windows :: Windows 10
Classifier: License :: OSI Approved :: MIT License
Classifier: Programming Language :: Python :: 3
Requires-Dist: aiohttp
